Lab_3/d_flipflop.v
module d_flipflop(d, clk, reset, q);
input d, clk, reset;
output q;
reg q;

always@(posedge clk or posedge reset)
	if(reset)
 		q <= 1'b0;
	else
		q <= d;

endmodule

Lab_3/d_flipflop_tb.v
`include "d_flipflop.v"

module d_flipflop_tb;
reg d, clk, reset;
wire q;

initial
	begin
		$dumpfile("d_flipflop_tb.vcd");
		$dumpvars(0,d_flipflop_tb);
end

d_flipflop d1(d, clk, reset, q);

initial
	begin
		reset=0;
		clk =0;
		d=0;
end

always 
#5  clk =  ! clk; 

always #10 d=~d;
/*
initial
	begin
		#5 reset =1'b1;
		d=0;
		#5 d = 1'b1;
end
*/

always@(*)
	begin
 		$display("d=%b, clk=%b, rst=%b, q=%b\n", d, clk, reset, q);
	end 

initial
	#100 $finish;
endmodule

Lab_3/d_flipflop_tb.vcd
$date
	Fri Aug 16 16:31:50 2019
$end
$version
	Icarus Verilog
$end
$timescale
	1s
$end
$scope module d_flipflop_tb $end
$var wire 1 ! q $end
$var reg 1 " clk $end
$var reg 1 # d $end
$var reg 1 $ reset $end
$scope module d1 $end
$var wire 1 % clk $end
$var wire 1 & d $end
$var wire 1 ' reset $end
$var reg 1 ( q $end
$upscope $end
$upscope $end
$enddefinitions $end
#0
$dumpvars
x(
0'
0&
0%
0$
0#
0"
x!
$end
#5
0(
0!
1"
1%
#10
0"
0%
1#
1&
#15
1(
1!
1"
1%
#20
0"
0%
0#
0&
#25
0(
0!
1"
1%
#30
0"
0%
1#
1&
#35
1(
1!
1"
1%
#40
0"
0%
0#
0&
#45
0(
0!
1"
1%
#50
0"
0%
1#
1&
#55
1(
1!
1"
1%
#60
0"
0%
0#
0&
#65
0(
0!
1"
1%
#70
0"
0%
1#
1&
#75
1(
1!
1"
1%
#80
0"
0%
0#
0&
#85
0(
0!
1"
1%
#90
0"
0%
1#
1&
#95
1(
1!
1"
1%
#100
0"
0%
0#
0&
