Lab_3/jk_flipflop.v
module jk_flipflop(j, k, clk, reset, q);

input j, k, clk, reset;
output q;
reg q;

always@(posedge clk or posedge reset)
	if(reset)
 		q <= 1'b0;
	else
		q <= ((!k)&q)|(j&(!q));	

endmodule

Lab_3/jk_flipflop_tb.v
`include "jk_flipflop.v"

module jk_flipflop_tb;
reg j, k, clk, reset;
wire q;

initial
	begin
		$dumpfile("jk_flipflop_tb.vcd");
		$dumpvars(0,jk_flipflop_tb);
end

jk_flipflop j1(j, k, clk, reset, q);

initial
	begin
		reset=1;
		clk =0;
		j=0;
		k=0;
end

always 
#5  clk = !clk; 

always
#5 reset=0;

always
	#5 k = !k;
always
	#10 j = !j;
always
	#15 k = !k;

/*
initial
	begin
		#5 reset =1'b1;
		d=0;
		#5 d = 1'b1;
end
*/

always@(*)
	begin
 		$display($time, "j=%b, k=%b, clk=%b, rst=%b, q=%b\n", j, k, clk, reset, q);
	end 

initial
	#100 $finish;
endmodule

Lab_3/jk_flipflop_tb.vcd
$date
	Fri Aug 16 17:39:06 2019
$end
$version
	Icarus Verilog
$end
$timescale
	1s
$end
$scope module jk_flipflop_tb $end
$var wire 1 ! q $end
$var reg 1 " clk $end
$var reg 1 # j $end
$var reg 1 $ k $end
$var reg 1 % reset $end
$scope module j1 $end
$var wire 1 & clk $end
$var wire 1 ' j $end
$var wire 1 ( k $end
$var wire 1 ) reset $end
$var reg 1 * q $end
$upscope $end
$upscope $end
$enddefinitions $end
#0
$dumpvars
0*
1)
0(
0'
0&
1%
0$
0#
0"
0!
$end
#5
1$
1(
0%
0)
1"
1&
#10
0$
0(
0"
0&
1#
1'
#15
1*
1!
1"
1&
0$
0(
#20
1$
1(
0"
0&
0#
0'
#25
0$
0(
1"
1&
#30
0"
0&
1#
1'
0$
0(
#35
0*
0!
1$
1(
1"
1&
#40
0$
0(
0"
0&
0#
0'
#45
1"
1&
0$
0(
#50
1$
1(
0"
0&
1#
1'
#55
1*
1!
0$
0(
1"
1&
#60
0"
0&
0#
0'
0$
0(
#65
0*
0!
1$
1(
1"
1&
#70
0$
0(
0"
0&
1#
1'
#75
1*
1!
1"
1&
0$
0(
#80
1$
1(
0"
0&
0#
0'
#85
0$
0(
1"
1&
#90
0"
0&
1#
1'
0$
0(
#95
0*
0!
1$
1(
1"
1&
#100
0$
0(
0"
0&
0#
0'
