Lab_3/jk_flipflop.v
module jk_flipflop(j, k, clk, reset, q);

input j, k, clk, reset;
output q;
reg q;

always@(posedge clk or posedge reset)
	if(reset)
 		q <= 1'b0;
	else
		q <= ((!k)&q)|(j&(!q));	

endmodule

Lab_3/syn_up_down_counter.v
`include "jk_flipflop.v"

module syn_up_down_counter(j, k, clk, reset, u, q);

input j, k, clk, reset, u;
output [3:0] q;

//always@(posedge clk or posedge reset)
	jk_flipflop JKFF_0(j, k, clk, reset, q[0]);
	jk_flipflop JKFF_1((u & q[0])|(!u & !q[0]), (u & q[0])|(!u & !q[0]), clk, reset, q[1]);
	jk_flipflop JKFF_2((u & q[0] & q[1])|(!u & !q[0] & !q[1]), (u & q[0] & q[1])|(!u & !q[0] & !q[1]), clk, reset, q[2]);
	jk_flipflop JKFF_3((u & q[0] & q[1] & q[2])|(!u & !q[0] & !q[1] & !q[2]), (u & q[0] & q[1] & q[2])|(!u & !q[0] & !q[1] & !q[2]), clk, reset, q[3]);

endmodule

Lab_3/syn_up_down_counter_tb.v
`include "syn_up_down_counter.v"

module top;
reg j, k, clk, reset, u;
wire [3:0] q;

initial
	begin
		$dumpfile("syn_up_down_counter_tb.vcd");
		$dumpvars(0,top);
end

initial
	begin
		reset=1;
		clk=1;
		j=1; k=1;
		u=1;
end

always
	begin
	#5 clk=!clk;
	reset = 1'b0;
	end
always
	#160 u=0;

syn_up_down_counter SUDC_1(j, k, clk, reset, u, q);

always @(*)
	begin
		$monitor("j = %b,  k = %b, r = %b,  u = %b, q=%b", j, k, reset, u, q);
	end

initial
	#320 $finish;

endmodule

Lab_3/syn_up_down_counter_tb.vcd
$date
	Fri Aug 23 18:19:30 2019
$end
$version
	Icarus Verilog
$end
$timescale
	1s
$end
$scope module top $end
$var wire 4 ! q [3:0] $end
$var reg 1 " clk $end
$var reg 1 # j $end
$var reg 1 $ k $end
$var reg 1 % reset $end
$var reg 1 & u $end
$scope module SUDC_1 $end
$var wire 1 ' clk $end
$var wire 1 ( j $end
$var wire 1 ) k $end
$var wire 4 * q [3:0] $end
$var wire 1 + reset $end
$var wire 1 , u $end
$scope module JKFF_0 $end
$var wire 1 ' clk $end
$var wire 1 ( j $end
$var wire 1 ) k $end
$var wire 1 + reset $end
$var reg 1 - q $end
$upscope $end
$scope module JKFF_1 $end
$var wire 1 ' clk $end
$var wire 1 . j $end
$var wire 1 / k $end
$var wire 1 + reset $end
$var reg 1 0 q $end
$upscope $end
$scope module JKFF_2 $end
$var wire 1 ' clk $end
$var wire 1 1 j $end
$var wire 1 2 k $end
$var wire 1 + reset $end
$var reg 1 3 q $end
$upscope $end
$scope module JKFF_3 $end
$var wire 1 ' clk $end
$var wire 1 4 j $end
$var wire 1 5 k $end
$var wire 1 + reset $end
$var reg 1 6 q $end
$upscope $end
$upscope $end
$upscope $end
$enddefinitions $end
#0
$dumpvars
06
05
04
03
02
01
00
0/
0.
0-
1,
1+
b0 *
1)
1(
1'
1&
1%
1$
1#
1"
b0 !
$end
#5
0%
0+
0"
0'
#10
1.
1/
1-
b1 !
b1 *
1"
1'
#15
0"
0'
#20
0.
0/
01
02
0-
10
b10 !
b10 *
1"
1'
#25
0"
0'
#30
11
12
1.
1/
1-
b11 !
b11 *
1"
1'
#35
0"
0'
#40
0.
0/
01
02
04
05
0-
00
13
b100 !
b100 *
1"
1'
#45
0"
0'
#50
1.
1/
1-
b101 !
b101 *
1"
1'
#55
0"
0'
#60
04
05
0.
0/
01
02
0-
10
b110 !
b110 *
1"
1'
#65
0"
0'
#70
14
15
11
12
1.
1/
1-
b111 !
b111 *
1"
1'
#75
0"
0'
#80
0.
0/
01
02
04
05
0-
00
03
16
b1000 !
b1000 *
1"
1'
#85
0"
0'
#90
1.
1/
1-
b1001 !
b1001 *
1"
1'
#95
0"
0'
#100
0.
0/
01
02
0-
10
b1010 !
b1010 *
1"
1'
#105
0"
0'
#110
11
12
1.
1/
1-
b1011 !
b1011 *
1"
1'
#115
0"
0'
#120
0.
0/
01
02
04
05
0-
00
13
b1100 !
b1100 *
1"
1'
#125
0"
0'
#130
1.
1/
1-
b1101 !
b1101 *
1"
1'
#135
0"
0'
#140
04
05
0.
0/
01
02
0-
10
b1110 !
b1110 *
1"
1'
#145
0"
0'
#150
14
15
11
12
1.
1/
1-
b1111 !
b1111 *
1"
1'
#155
0"
0'
#160
0-
00
03
06
b0 !
b0 *
14
15
11
12
1.
1/
1"
1'
0&
0,
#165
0"
0'
#170
04
05
01
02
0.
0/
16
13
10
1-
b1111 !
b1111 *
1"
1'
#175
0"
0'
#180
1.
1/
0-
b1110 !
b1110 *
1"
1'
#185
0"
0'
#190
0.
0/
00
1-
b1101 !
b1101 *
1"
1'
#195
0"
0'
#200
11
12
1.
1/
0-
b1100 !
b1100 *
1"
1'
#205
0"
0'
#210
01
02
0.
0/
03
10
1-
b1011 !
b1011 *
1"
1'
#215
0"
0'
#220
1.
1/
0-
b1010 !
b1010 *
1"
1'
#225
0"
0'
#230
0.
0/
00
1-
b1001 !
b1001 *
1"
1'
#235
0"
0'
#240
14
15
11
12
1.
1/
0-
b1000 !
b1000 *
1"
1'
#245
0"
0'
#250
04
05
01
02
0.
0/
06
13
10
1-
b111 !
b111 *
1"
1'
#255
0"
0'
#260
1.
1/
0-
b110 !
b110 *
1"
1'
#265
0"
0'
#270
0.
0/
00
1-
b101 !
b101 *
1"
1'
#275
0"
0'
#280
11
12
1.
1/
0-
b100 !
b100 *
1"
1'
#285
0"
0'
#290
01
02
0.
0/
03
10
1-
b11 !
b11 *
1"
1'
#295
0"
0'
#300
1.
1/
0-
b10 !
b10 *
1"
1'
#305
0"
0'
#310
0.
0/
00
1-
b1 !
b1 *
1"
1'
#315
0"
0'
#320
14
15
11
12
1.
1/
0-
b0 !
b0 *
1"
1'
